Brewgorithm-2.1.2.dist-info/DESCRIPTION.rst
Brewgorithm-2.1.2.dist-info/METADATA
Brewgorithm-2.1.2.dist-info/RECORD
Brewgorithm-2.1.2.dist-info/WHEEL
Brewgorithm-2.1.2.dist-info/metadata.json
Brewgorithm-2.1.2.dist-info/top_level.txt
brewgorithm/__init__.py
brewgorithm/language/__init__.py
brewgorithm/language/cleaning.py
brewgorithm/language/config.py
brewgorithm/language/parsing.py
brewgorithm/language/sense_emb.py
brewgorithm/neural/__init__.py
brewgorithm/neural/beer2vec/__init__.py
brewgorithm/neural/beer2vec/access_ext.py
brewgorithm/neural/beer2vec/config.py
brewgorithm/neural/beer2vec/demo.py
brewgorithm/neural/beer2vec/load.py
brewgorithm/neural/beer_emb/__init__.py
brewgorithm/neural/beer_emb/access_ext.py
brewgorithm/neural/beer_emb/config.py
brewgorithm/neural/beer_emb/demo.py
brewgorithm/neural/beer_emb/load.py
brewgorithm/neural/word_weighter/__init__.py
brewgorithm/neural/word_weighter/access_ext.py
brewgorithm/neural/word_weighter/config.py
brewgorithm/neural/word_weighter/demo.py
brewgorithm/neural/word_weighter/load.py
brewgorithm/neural/word_weighter/model.py
brewgorithm/neural/word_weighter/dev/__init__.py
brewgorithm/neural/word_weighter/dev/data.py
brewgorithm/neural/word_weighter/dev/preprocessing.py
brewgorithm/neural/word_weighter/dev/train.py
