Metadata-Version: 2.0
Name: Brewgorithm
Version: 2.1.2
Summary: Machine Learning Library For Beer
Home-page: https://github.com/ericzhao28/brewgorithm_devkit.git
Author: Eric Zhao, Brewgorithm, and Contributors
Author-email: elzhao@caltech.edu
License: MIT
Keywords: beer data ai machine_learning
Platform: UNKNOWN
Classifier: Development Status :: 4 - Beta
Classifier: Intended Audience :: Developers
Classifier: Topic :: Scientific/Engineering :: Artificial Intelligence
Classifier: License :: OSI Approved :: MIT License
Classifier: Programming Language :: Python :: 3
Classifier: Programming Language :: Python :: 3.3
Classifier: Programming Language :: Python :: 3.4
Classifier: Programming Language :: Python :: 3.5
Requires-Dist: gensim
Requires-Dist: h5py
Requires-Dist: keras
Requires-Dist: spacy
Requires-Dist: tensorflow
